.gitignore
.gitmodules
CMakeLists.txt
README.md
pyproject.toml
setup.cfg
setup.py
.github/workflows/ci.yml
examples/opencv_example.py
examples/simple.py
extern/quirc/.gitignore
extern/quirc/LICENSE
extern/quirc/Makefile
extern/quirc/README.md
extern/quirc/demo/camera.c
extern/quirc/demo/camera.h
extern/quirc/demo/convert.c
extern/quirc/demo/convert.h
extern/quirc/demo/demo.c
extern/quirc/demo/demo_opencv.cxx
extern/quirc/demo/demoutil.c
extern/quirc/demo/demoutil.h
extern/quirc/demo/dthash.c
extern/quirc/demo/dthash.h
extern/quirc/demo/mjpeg.c
extern/quirc/demo/mjpeg.h
extern/quirc/demo/scanner.c
extern/quirc/lib/decode.c
extern/quirc/lib/identify.c
extern/quirc/lib/quirc.c
extern/quirc/lib/quirc.h
extern/quirc/lib/quirc_internal.h
extern/quirc/lib/version_db.c
extern/quirc/tests/dbgutil.c
extern/quirc/tests/dbgutil.h
extern/quirc/tests/inspect.c
extern/quirc/tests/inspect_opencv.cxx
extern/quirc/tests/qrtest.c
include/quirc++/data.h
include/quirc++/decoder.h
resources/helloworld.dat
resources/helloworld.png
src/decode.cpp
src/decoder.cpp
src/main.cpp
src/pyquirc.cpp
src/pyquirc.egg-info/PKG-INFO
src/pyquirc.egg-info/SOURCES.txt
src/pyquirc.egg-info/dependency_links.txt
src/pyquirc.egg-info/entry_points.txt
src/pyquirc.egg-info/requires.txt
src/pyquirc.egg-info/top_level.txt
src/quirc/__init__.py
src/quirc/__main__.py
src/quirc/tests/__init__.py
src/quirc/tests/conftest.py
src/quirc/tests/test_decode.py
src/quirc/tests/test_low_level.py