Metadata-Version: 2.1
Name: pyquirc
Version: 0.2.0.post1
Summary: Python bindings for quirc, via pybind11
Author: Maximilian Nöthe
Author-email: maximilian.noethe@tu-dortmund.de
License: MIT
Classifier: License :: OSI Approved :: MIT License
Classifier: Programming Language :: Python :: 3
Classifier: Programming Language :: Python :: 3.7
Classifier: Programming Language :: Python :: 3.8
Classifier: Programming Language :: Python :: 3.9
Classifier: Programming Language :: Python :: 3.10
Classifier: Programming Language :: Python :: 3.11
Classifier: Topic :: Scientific/Engineering :: Image Recognition
Classifier: Topic :: Scientific/Engineering :: Image Processing
Requires-Python: >=3.7
Provides-Extra: tests
